mkdocs_macros_test/__init__.py
mkdocs_macros_test-0.1.0.dist-info/LICENSE.md
mkdocs_macros_test-0.1.0.dist-info/METADATA
mkdocs_macros_test-0.1.0.dist-info/WHEEL
mkdocs_macros_test-0.1.0.dist-info/top_level.txt
mkdocs_macros_test-0.1.0.dist-info/RECORD
