Metadata-Version: 2.1
Name: mkdocs-macros-test
Version: 0.1.0
Summary: Test macros library for macros plugin
Home-page: UNKNOWN
Author: Laurent Franceschetti
Author-email: UNKNOWN
License: MIT
Platform: UNKNOWN
